mypysound/__init__.py
mypysound/mypysound.py
mypysound-2024.12.31.dist-info/LICENSE
mypysound-2024.12.31.dist-info/METADATA
mypysound-2024.12.31.dist-info/WHEEL
mypysound-2024.12.31.dist-info/RECORD
