Metadata-Version: 2.1
Name: mypysound
Version: 2024.12.31
Summary: A library to play sound on several platforms (including mobile using toga and chaquopy)
Home-page: https://github.com/Creative-Media-Group/pysound
License: MIT
Author: tct123
Author-email: 42028373+tct123@users.noreply.github.com
Requires-Python: >=3.9,<4.0
Classifier: License :: OSI Approved :: MIT License
Classifier: Programming Language :: Python :: 3
Classifier: Programming Language :: Python :: 3.9
Classifier: Programming Language :: Python :: 3.10
Classifier: Programming Language :: Python :: 3.11
Classifier: Programming Language :: Python :: 3.12
Classifier: Programming Language :: Python :: 3.13
Requires-Dist: playsound3
Project-URL: Repository, https://github.com/Creative-Media-Group/pysound
